nautikos/__init__.py
nautikos/cli.py
nautikos/manifests.py
nautikos/nautikos.py
nautikos/yaml.py
nautikos-0.3.4.dist-info/METADATA
nautikos-0.3.4.dist-info/WHEEL
nautikos-0.3.4.dist-info/entry_points.txt
nautikos-0.3.4.dist-info/RECORD
