Metadata-Version: 2.1
Name: nautikos
Version: 0.3.4
Summary: A CD tool for updating image tags in Kubernetes manifests
Home-page: https://www.github.com/janheindejong/nautikos
License: MIT
Keywords: Kubernetes,DevOps,CI/CD,Kustomize,GitOps
Author: Jan Hein de Jong
Author-email: janhein.dejong@gmail.com
Requires-Python: >=3.9,<4.0
Classifier: Development Status :: 3 - Alpha
Classifier: License :: OSI Approved :: MIT License
Classifier: Operating System :: OS Independent
Classifier: Programming Language :: Python :: 3
Classifier: Programming Language :: Python :: 3.9
Classifier: Programming Language :: Python :: 3.10
Classifier: Programming Language :: Python :: 3.11
Classifier: Topic :: Software Development
Classifier: Topic :: Software Development :: Build Tools
Requires-Dist: ruamel-yaml (>=0.17.21,<0.18.0)
Requires-Dist: typer (>=0.7.0,<0.8.0)
